Metadata-Version: 2.1
Name: aux-libraries
Version: 0.1
Summary: Funciones auxiliares para gestión de argumentos
Author-email: am.guerreroserna@gmail.com
